face_detector_plus/__init__.py
face_detector_plus/utils.py
face_detector_plus/detectors/__init__.py
face_detector_plus/detectors/caffemodel.py
face_detector_plus/detectors/cnn.py
face_detector_plus/detectors/hog.py
face_detector_plus/detectors/onnx_ultralight.py
face_detector_plus/detectors/utils.py
face_detector_plus-1.0.1.dist-info/METADATA
face_detector_plus-1.0.1.dist-info/WHEEL
face_detector_plus-1.0.1.dist-info/top_level.txt
face_detector_plus-1.0.1.dist-info/RECORD
