Metadata-Version: 2.1
Name: face_detector_plus
Version: 1.0.1
Summary: Light weight face detector high-level client with multiple detection techniques.
Home-page: https://github.com/huseyindas/face-detector-plus
Author: Huseyin Das
Author-email: hsyndass@gmail.com
License: Apache
Project-URL: Bug Reports, https://github.com/huseyindas/face-detector-plus/issues
Project-URL: Source, https://github.com/huseyindas/face-detector-plus
Project-URL: Documentation, https://github.com/huseyindas/face-detector-plus#documentation
Keywords: machine learning,face,detector,face detection,CNN,dlib,ultrafast,HOG,caffemodel
Classifier: Environment :: MacOS X
Classifier: Environment :: Win32 (MS Windows)
Classifier: Environment :: X11 Applications
Classifier: Intended Audience :: Developers
Classifier: Intended Audience :: Education
Classifier: Intended Audience :: End Users/Desktop
Classifier: Operating System :: OS Independent
Classifier: Programming Language :: Python :: 3 :: Only
Classifier: Topic :: Software Development
Classifier: Topic :: Software Development :: Build Tools
Classifier: Topic :: Software Development :: Libraries :: Python Modules
Classifier: Topic :: Software Development :: Widget Sets
Classifier: License :: OSI Approved :: Apache Software License
Requires-Python: >=3.9
Requires-Dist: dlib==19.24.5
Requires-Dist: onnxoptimizer==0.3.13
Requires-Dist: onnxruntime==1.18.1
Requires-Dist: opencv-contrib-python==4.10.0.84
Requires-Dist: tqdm==4.66.5
Requires-Dist: requests==2.32.3
